.gitignore
.travis.yml
CHANGES.txt
README.rst
buildout.cfg
setup.py
cleanup_zope_persistent_registry/__init__.py
cleanup_zope_persistent_registry/testing.py
cleanup_zope_persistent_registry.egg-info/PKG-INFO
cleanup_zope_persistent_registry.egg-info/SOURCES.txt
cleanup_zope_persistent_registry.egg-info/dependency_links.txt
cleanup_zope_persistent_registry.egg-info/not-zip-safe
cleanup_zope_persistent_registry.egg-info/requires.txt
cleanup_zope_persistent_registry.egg-info/top_level.txt
cleanup_zope_persistent_registry/tests/__init__.py
cleanup_zope_persistent_registry/tests/test_cleanup.py