Metadata-Version: 1.0
Name: cleanup-zope-persistent-registry
Version: 0.1.1
Summary: Cleanup of keys leftover in zope component registries
Home-page: UNKNOWN
Author: Godefroid Chapelle
Author-email: gotcha@bubblenet.be
License: UNKNOWN
Platform: UNKNOWN
